bibfixer/__init__.py
bibfixer/agent.py
bibfixer/cli.py
bibfixer/prompts/default.md
bibfixer-0.1.2.dist-info/licenses/LICENSE
bibfixer-0.1.2.dist-info/METADATA
bibfixer-0.1.2.dist-info/WHEEL
bibfixer-0.1.2.dist-info/entry_points.txt
bibfixer-0.1.2.dist-info/top_level.txt
bibfixer-0.1.2.dist-info/RECORD
