Metadata-Version: 2.4
Name: bibfixer
Version: 0.1.2
Summary: Fixes and standardizes BibTeX using LLM + web search
Author: Takashi Ishida
License: MIT License
Requires-Python: >=3.9
License-File: LICENSE
Requires-Dist: openai<2,>=1.107.0
Requires-Dist: bibtexparser<2,>=1.4.1
Dynamic: license-file
